{"name":"testFindNewCars","id":"TestPackage.CarTest:testFindNewCars","testCaseName":"TestPackage.CarTest","testSteps":[{"number":1,"description":"Test find new cars ","duration":7540,"startTime":"2022-12-12T15:13:09.737+05:30[Asia/Calcutta]","result":"SUCCESS","precondition":false,"level":0,"children":[{"number":2,"description":"Steps find new cars","duration":7540,"startTime":"2022-12-12T15:12:43.800+05:30[Asia/Calcutta]","screenshots":[{"screenshot":"d50b0731c25d91e9969d8161914a7efa8bf137ab133a53c9c5f6ab95e2a1e891.png","timeStamp":1670838171340,"screenshotName":"d50b0731c25d91e9969d8161914a7efa8bf137ab133a53c9c5f6ab95e2a1e891.png"}],"result":"SUCCESS","precondition":false,"level":1}]},{"number":3,"description":"Test find new cars ","duration":5387,"startTime":"2022-12-12T15:13:09.737+05:30[Asia/Calcutta]","result":"SUCCESS","precondition":false,"level":0,"children":[{"number":4,"description":"Steps find new cars","duration":5387,"startTime":"2022-12-12T15:13:03.370+05:30[Asia/Calcutta]","screenshots":[{"screenshot":"a2eba69c895402c9188d6a381b932b195a20a3e5708cccf22b1a1cca4d395ec7.png","timeStamp":1670838188757,"screenshotName":"a2eba69c895402c9188d6a381b932b195a20a3e5708cccf22b1a1cca4d395ec7.png"}],"result":"SUCCESS","precondition":false,"level":1}]}],"userStory":{"id":"TestPackage.CarTest","storyName":"Car test","displayName":"Car test","storyClassName":"TestPackage.CarTest","path":"","type":"feature"},"featureTag":{"name":"Car test","type":"feature","displayName":"Car test"},"title":"Test find new cars","tags":[{"name":"Car test","type":"feature","displayName":"Car test"}],"startTime":"2022-12-12T15:13:09.736+05:30[Asia/Calcutta]","duration":0,"isManualTestingUpToDate":false,"dataTable":{"headers":["brand","price"],"rows":[{"values":["Maruti Suzuki","password"],"lineNumber":0,"result":"SUCCESS"},{"values":["Hyundai","password_old"],"lineNumber":0,"result":"SUCCESS"}],"predefinedRows":false,"dataSetDescriptors":[{"startRow":0,"rowCount":0,"name":"","description":""}]},"manual":false,"result":"SUCCESS"}